odoo/addons/l10n_fr_department_product_origin/README.rst
odoo/addons/l10n_fr_department_product_origin/__init__.py
odoo/addons/l10n_fr_department_product_origin/__manifest__.py
odoo/addons/l10n_fr_department_product_origin/i18n/fr.po
odoo/addons/l10n_fr_department_product_origin/i18n/l10n_fr_department_product_origin.pot
odoo/addons/l10n_fr_department_product_origin/models/__init__.py
odoo/addons/l10n_fr_department_product_origin/models/product_product.py
odoo/addons/l10n_fr_department_product_origin/models/product_template.py
odoo/addons/l10n_fr_department_product_origin/readme/CONTRIBUTORS.rst
odoo/addons/l10n_fr_department_product_origin/readme/DESCRIPTION.rst
odoo/addons/l10n_fr_department_product_origin/static/description/icon.png
odoo/addons/l10n_fr_department_product_origin/static/description/index.html
odoo/addons/l10n_fr_department_product_origin/static/description/product_form.png
odoo/addons/l10n_fr_department_product_origin/tests/__init__.py
odoo/addons/l10n_fr_department_product_origin/tests/test_module.py
odoo/addons/l10n_fr_department_product_origin/views/view_product_product.xml
odoo/addons/l10n_fr_department_product_origin/views/view_product_template.xml
odoo_addon_l10n_fr_department_product_origin-16.0.1.0.0.4.dist-info/METADATA
odoo_addon_l10n_fr_department_product_origin-16.0.1.0.0.4.dist-info/WHEEL
odoo_addon_l10n_fr_department_product_origin-16.0.1.0.0.4.dist-info/top_level.txt
odoo_addon_l10n_fr_department_product_origin-16.0.1.0.0.4.dist-info/RECORD
