Metadata-Version: 2.1
Name: odoo-addon-l10n_fr_department_product_origin
Version: 16.0.1.0.0.4
Summary: Product Origin (French Departments)
Home-page: https://github.com/OCA/l10n-france
Author: GRAP,Odoo Community Association (OCA)
Author-email: support@odoo-community.org
License: AGPL-3
Classifier: Programming Language :: Python
Classifier: Framework :: Odoo
Classifier: Framework :: Odoo :: 16.0
Classifier: License :: OSI Approved :: GNU Affero General Public License v3
Requires-Python: >=3.10
Requires-Dist: odoo-addon-l10n-fr-department <16.1dev,>=16.0dev
Requires-Dist: odoo-addon-product-origin <16.1dev,>=16.0dev
Requires-Dist: odoo <16.1dev,>=16.0a
